to-sub/__init__.py
to-sub/__main__.py
to-sub/app.py
to-sub/ffmpeg.py
to-sub/log.py
to-sub/main.py
to-sub/media.py
to-sub/test.py
to-sub/youtube.py
tosync/__init__.py
tosync/__main__.py
tosync/app.py
tosync/ffmpeg.py
tosync/log.py
tosync/main.py
tosync/media.py
tosync/run.py
tosync/test.py
tosync/testing.py
tosync/youtube.py
tosync-1.0.2.dist-info/METADATA
tosync-1.0.2.dist-info/WHEEL
tosync-1.0.2.dist-info/entry_points.txt
tosync-1.0.2.dist-info/top_level.txt
tosync-1.0.2.dist-info/RECORD
