Metadata-Version: 2.1
Name: tosync
Version: 1.0.2
Summary: Transcript to subtitles
Home-page: https://github.com/steph-tseng/to-sub
Author: Stephanie Tseng
Author-email: lordnyx1031@gmail.com
License: UNKNOWN
Platform: UNKNOWN
Classifier: Programming Language :: Python :: 3.9
Requires-Dist: feedparser
Requires-Dist: html2text
